nnvision_camera/__init__.py
nnvision_camera/main.py
nnvision_camera/QR-code-setup/capture_qr_code.py
nnvision_camera-0.0.18.dist-info/licenses/LICENSE
nnvision_camera-0.0.18.dist-info/METADATA
nnvision_camera-0.0.18.dist-info/WHEEL
nnvision_camera-0.0.18.dist-info/entry_points.txt
nnvision_camera-0.0.18.dist-info/top_level.txt
nnvision_camera-0.0.18.dist-info/RECORD
