Metadata-Version: 2.4
Name: nnvision_camera
Version: 0.0.18
Summary: Client library for the nnvision camera API
Author-email: Julien Jehl <julien.jehl@protecia.net>
License: MIT
Project-URL: Homepage, https://github.com/Protecia/nnvision_camera
Project-URL: Source, https://github.com/Protecia/nnvision_camera.git
Classifier: Programming Language :: Python :: 3
Classifier: License :: OSI Approved :: MIT License
Classifier: Operating System :: OS Independent
Requires-Python: >=3.11
License-File: LICENSE
Requires-Dist: pyzbar>=0.1.9
Requires-Dist: pillow>=11.2.1
Requires-Dist: python-crontab>=3.2.0
Requires-Dist: requests>=2.32.3
Dynamic: license-file
